{
    "id": 144382983,
    "name": "Lav Never Clear",
    "author": "Lavender",
    "creators": ["Lavender"],
    "verifier": "Lavender",
    "verification": "https://youtu.be/Ier5JuuVQXM?si=qmCWHQWnGreNZGM-",
    "percentToQualify": "56",
    "password": "Free To Copy",
    "records": [
     {
            "user": "Orb",
            "link": "https://medal.tv/games/geometry-dash/clips/n79iUITjoGVw5u3Ob?invite=cr-MSxQSlMsNjc0ODkzNzAy",
            "percent": 100,
            "hz": 240
        }
    ]
}
